<?xml version="1.0"?>
<testResults>
  <FitNesseVersion>v20230503</FitNesseVersion>
  <rootPath>FrontPage.BankomatIoSuite.TestWyplataGotowki</rootPath>
  <result>
    <counts>
      <right>15</right>
      <wrong>0</wrong>
      <ignores>0</ignores>
      <exceptions>0</exceptions>
    </counts>
    <date>2026-02-02T10:32:08+01:00</date>
    <runTimeInMillis>62</runTimeInMillis>
    <content>&lt;div class="collapsible closed"&gt;&lt;ul&gt;&lt;li&gt;&lt;a href='#' class='expandall'&gt;Expand&lt;/a&gt;&lt;/li&gt;&lt;li&gt;&lt;a href='#' class='collapseall'&gt;Collapse&lt;/a&gt;&lt;/li&gt;&lt;/ul&gt;
	&lt;p class="title"&gt;Included page: &lt;a href="FrontPage.BankomatIoSuite.SetUp"&gt;.FrontPage.BankomatIoSuite.SetUp&lt;/a&gt; &lt;a href="FrontPage.BankomatIoSuite.SetUp?edit&amp;amp;redirectToReferer=true&amp;amp;redirectAction=" class="edit"&gt;(edit)&lt;/a&gt;&lt;/p&gt;
	&lt;div&gt;&lt;table&gt;
	&lt;tr class="slimRowTitle"&gt;
		&lt;td&gt;&lt;span class="pass"&gt;testyfitnesse.SetUp&lt;/span&gt;&lt;/td&gt;
	&lt;/tr&gt;
&lt;/table&gt;
&lt;/div&gt;
&lt;/div&gt;
&lt;br/&gt;Test przypadku użycia: Wypłata gotówki z bankomatu&lt;br/&gt;&lt;br/&gt;&lt;table&gt;
	&lt;tr class="slimRowTitle"&gt;
		&lt;td colspan="6"&gt;&lt;span class="pass"&gt;testyfitnesse.TestWyplatyGotowki&lt;/span&gt;&lt;/td&gt;
	&lt;/tr&gt;
	&lt;tr class="slimRowTitle"&gt;
		&lt;td&gt;idKarty&lt;/td&gt;
		&lt;td&gt;pin&lt;/td&gt;
		&lt;td&gt;kwotaWyplaty&lt;/td&gt;
		&lt;td&gt;wykonajWyplateGotowki?&lt;/td&gt;
		&lt;td&gt;sprawdzSaldoPoWyplacie?&lt;/td&gt;
		&lt;td&gt;sprawdzCzyKartaNieZablokowana?&lt;/td&gt;
	&lt;/tr&gt;
	&lt;tr class="slimRowColor1"&gt;
		&lt;td&gt;1001&lt;/td&gt;
		&lt;td&gt;1234&lt;/td&gt;
		&lt;td&gt;100.00&lt;/td&gt;
		&lt;td&gt;&lt;span class="pass"&gt;true&lt;/span&gt;&lt;/td&gt;
		&lt;td&gt;&lt;span class="pass"&gt;900.0&lt;/span&gt;&lt;/td&gt;
		&lt;td&gt;&lt;span class="pass"&gt;true&lt;/span&gt;&lt;/td&gt;
	&lt;/tr&gt;
	&lt;tr class="slimRowColor0"&gt;
		&lt;td&gt;1001&lt;/td&gt;
		&lt;td&gt;1234&lt;/td&gt;
		&lt;td&gt;200.00&lt;/td&gt;
		&lt;td&gt;&lt;span class="pass"&gt;true&lt;/span&gt;&lt;/td&gt;
		&lt;td&gt;&lt;span class="pass"&gt;700.0&lt;/span&gt;&lt;/td&gt;
		&lt;td&gt;&lt;span class="pass"&gt;true&lt;/span&gt;&lt;/td&gt;
	&lt;/tr&gt;
	&lt;tr class="slimRowColor1"&gt;
		&lt;td&gt;1002&lt;/td&gt;
		&lt;td&gt;5678&lt;/td&gt;
		&lt;td&gt;50.00&lt;/td&gt;
		&lt;td&gt;&lt;span class="pass"&gt;true&lt;/span&gt;&lt;/td&gt;
		&lt;td&gt;&lt;span class="pass"&gt;450.0&lt;/span&gt;&lt;/td&gt;
		&lt;td&gt;&lt;span class="pass"&gt;true&lt;/span&gt;&lt;/td&gt;
	&lt;/tr&gt;
	&lt;tr class="slimRowColor0"&gt;
		&lt;td&gt;1001&lt;/td&gt;
		&lt;td&gt;9999&lt;/td&gt;
		&lt;td&gt;100.00&lt;/td&gt;
		&lt;td&gt;&lt;span class="pass"&gt;false&lt;/span&gt;&lt;/td&gt;
		&lt;td&gt;&lt;span class="pass"&gt;700.0&lt;/span&gt;&lt;/td&gt;
		&lt;td&gt;&lt;span class="pass"&gt;true&lt;/span&gt;&lt;/td&gt;
	&lt;/tr&gt;
	&lt;tr class="slimRowColor1"&gt;
		&lt;td&gt;1003&lt;/td&gt;
		&lt;td&gt;9999&lt;/td&gt;
		&lt;td&gt;6000.00&lt;/td&gt;
		&lt;td&gt;&lt;span class="pass"&gt;false&lt;/span&gt;&lt;/td&gt;
		&lt;td&gt;&lt;span class="pass"&gt;2500.0&lt;/span&gt;&lt;/td&gt;
		&lt;td&gt;&lt;span class="pass"&gt;true&lt;/span&gt;&lt;/td&gt;
	&lt;/tr&gt;
&lt;/table&gt;
</content>
    <relativePageName>TestWyplataGotowki</relativePageName>
    <instructions>
      <instructionResult>
        <instruction>{id='decisionTable_0_0', instruction='make', instanceName='decisionTable_0', className='testyfitnesse.SetUp', args=[]}</instruction>
        <slimResult>pass(testyfitnesse.SetUp)</slimResult>
        <expectation>
          <status>pass</status>
          <instructionId>decisionTable_0_0</instructionId>
          <col>0</col>
          <row>0</row>
          <type>ConstructionExpectation</type>
          <evaluationMessage>testyfitnesse.SetUp</evaluationMessage>
        </expectation>
      </instructionResult>
      <instructionResult>
        <instruction>{id='decisionTable_1_0', instruction='make', instanceName='decisionTable_1', className='testyfitnesse.TestWyplatyGotowki', args=[]}</instruction>
        <slimResult>pass(testyfitnesse.TestWyplatyGotowki)</slimResult>
        <expectation>
          <status>pass</status>
          <instructionId>decisionTable_1_0</instructionId>
          <col>0</col>
          <row>0</row>
          <type>ConstructionExpectation</type>
          <evaluationMessage>testyfitnesse.TestWyplatyGotowki</evaluationMessage>
        </expectation>
      </instructionResult>
      <instructionResult>
        <instruction>{id='decisionTable_1_4', instruction='call', instanceName='decisionTable_1', methodName='setIdKarty', args=[1001]}</instruction>
        <slimResult></slimResult>
        <expectation>
          <instructionId>decisionTable_1_4</instructionId>
          <col>0</col>
          <row>2</row>
          <type>VoidReturnExpectation</type>
        </expectation>
      </instructionResult>
      <instructionResult>
        <instruction>{id='decisionTable_1_5', instruction='call', instanceName='decisionTable_1', methodName='setPin', args=[1234]}</instruction>
        <slimResult></slimResult>
        <expectation>
          <instructionId>decisionTable_1_5</instructionId>
          <col>1</col>
          <row>2</row>
          <type>VoidReturnExpectation</type>
        </expectation>
      </instructionResult>
      <instructionResult>
        <instruction>{id='decisionTable_1_6', instruction='call', instanceName='decisionTable_1', methodName='setKwotaWyplaty', args=[100.00]}</instruction>
        <slimResult></slimResult>
        <expectation>
          <instructionId>decisionTable_1_6</instructionId>
          <col>2</col>
          <row>2</row>
          <type>VoidReturnExpectation</type>
        </expectation>
      </instructionResult>
      <instructionResult>
        <instruction>{id='decisionTable_1_8', instruction='call', instanceName='decisionTable_1', methodName='wykonajWyplateGotowki', args=[]}</instruction>
        <slimResult>pass(true)</slimResult>
        <expectation>
          <status>pass</status>
          <instructionId>decisionTable_1_8</instructionId>
          <col>3</col>
          <row>2</row>
          <type>ReturnedValueExpectation</type>
          <evaluationMessage>true</evaluationMessage>
        </expectation>
      </instructionResult>
      <instructionResult>
        <instruction>{id='decisionTable_1_9', instruction='call', instanceName='decisionTable_1', methodName='sprawdzSaldoPoWyplacie', args=[]}</instruction>
        <slimResult>pass(900.0)</slimResult>
        <expectation>
          <status>pass</status>
          <instructionId>decisionTable_1_9</instructionId>
          <col>4</col>
          <row>2</row>
          <type>ReturnedValueExpectation</type>
          <evaluationMessage>900.0</evaluationMessage>
        </expectation>
      </instructionResult>
      <instructionResult>
        <instruction>{id='decisionTable_1_10', instruction='call', instanceName='decisionTable_1', methodName='sprawdzCzyKartaNieZablokowana', args=[]}</instruction>
        <slimResult>pass(true)</slimResult>
        <expectation>
          <status>pass</status>
          <instructionId>decisionTable_1_10</instructionId>
          <col>5</col>
          <row>2</row>
          <type>ReturnedValueExpectation</type>
          <evaluationMessage>true</evaluationMessage>
        </expectation>
      </instructionResult>
      <instructionResult>
        <instruction>{id='decisionTable_1_12', instruction='call', instanceName='decisionTable_1', methodName='setIdKarty', args=[1001]}</instruction>
        <slimResult></slimResult>
        <expectation>
          <instructionId>decisionTable_1_12</instructionId>
          <col>0</col>
          <row>3</row>
          <type>VoidReturnExpectation</type>
        </expectation>
      </instructionResult>
      <instructionResult>
        <instruction>{id='decisionTable_1_13', instruction='call', instanceName='decisionTable_1', methodName='setPin', args=[1234]}</instruction>
        <slimResult></slimResult>
        <expectation>
          <instructionId>decisionTable_1_13</instructionId>
          <col>1</col>
          <row>3</row>
          <type>VoidReturnExpectation</type>
        </expectation>
      </instructionResult>
      <instructionResult>
        <instruction>{id='decisionTable_1_14', instruction='call', instanceName='decisionTable_1', methodName='setKwotaWyplaty', args=[200.00]}</instruction>
        <slimResult></slimResult>
        <expectation>
          <instructionId>decisionTable_1_14</instructionId>
          <col>2</col>
          <row>3</row>
          <type>VoidReturnExpectation</type>
        </expectation>
      </instructionResult>
      <instructionResult>
        <instruction>{id='decisionTable_1_16', instruction='call', instanceName='decisionTable_1', methodName='wykonajWyplateGotowki', args=[]}</instruction>
        <slimResult>pass(true)</slimResult>
        <expectation>
          <status>pass</status>
          <instructionId>decisionTable_1_16</instructionId>
          <col>3</col>
          <row>3</row>
          <type>ReturnedValueExpectation</type>
          <evaluationMessage>true</evaluationMessage>
        </expectation>
      </instructionResult>
      <instructionResult>
        <instruction>{id='decisionTable_1_17', instruction='call', instanceName='decisionTable_1', methodName='sprawdzSaldoPoWyplacie', args=[]}</instruction>
        <slimResult>pass(700.0)</slimResult>
        <expectation>
          <status>pass</status>
          <instructionId>decisionTable_1_17</instructionId>
          <col>4</col>
          <row>3</row>
          <type>ReturnedValueExpectation</type>
          <evaluationMessage>700.0</evaluationMessage>
        </expectation>
      </instructionResult>
      <instructionResult>
        <instruction>{id='decisionTable_1_18', instruction='call', instanceName='decisionTable_1', methodName='sprawdzCzyKartaNieZablokowana', args=[]}</instruction>
        <slimResult>pass(true)</slimResult>
        <expectation>
          <status>pass</status>
          <instructionId>decisionTable_1_18</instructionId>
          <col>5</col>
          <row>3</row>
          <type>ReturnedValueExpectation</type>
          <evaluationMessage>true</evaluationMessage>
        </expectation>
      </instructionResult>
      <instructionResult>
        <instruction>{id='decisionTable_1_20', instruction='call', instanceName='decisionTable_1', methodName='setIdKarty', args=[1002]}</instruction>
        <slimResult></slimResult>
        <expectation>
          <instructionId>decisionTable_1_20</instructionId>
          <col>0</col>
          <row>4</row>
          <type>VoidReturnExpectation</type>
        </expectation>
      </instructionResult>
      <instructionResult>
        <instruction>{id='decisionTable_1_21', instruction='call', instanceName='decisionTable_1', methodName='setPin', args=[5678]}</instruction>
        <slimResult></slimResult>
        <expectation>
          <instructionId>decisionTable_1_21</instructionId>
          <col>1</col>
          <row>4</row>
          <type>VoidReturnExpectation</type>
        </expectation>
      </instructionResult>
      <instructionResult>
        <instruction>{id='decisionTable_1_22', instruction='call', instanceName='decisionTable_1', methodName='setKwotaWyplaty', args=[50.00]}</instruction>
        <slimResult></slimResult>
        <expectation>
          <instructionId>decisionTable_1_22</instructionId>
          <col>2</col>
          <row>4</row>
          <type>VoidReturnExpectation</type>
        </expectation>
      </instructionResult>
      <instructionResult>
        <instruction>{id='decisionTable_1_24', instruction='call', instanceName='decisionTable_1', methodName='wykonajWyplateGotowki', args=[]}</instruction>
        <slimResult>pass(true)</slimResult>
        <expectation>
          <status>pass</status>
          <instructionId>decisionTable_1_24</instructionId>
          <col>3</col>
          <row>4</row>
          <type>ReturnedValueExpectation</type>
          <evaluationMessage>true</evaluationMessage>
        </expectation>
      </instructionResult>
      <instructionResult>
        <instruction>{id='decisionTable_1_25', instruction='call', instanceName='decisionTable_1', methodName='sprawdzSaldoPoWyplacie', args=[]}</instruction>
        <slimResult>pass(450.0)</slimResult>
        <expectation>
          <status>pass</status>
          <instructionId>decisionTable_1_25</instructionId>
          <col>4</col>
          <row>4</row>
          <type>ReturnedValueExpectation</type>
          <evaluationMessage>450.0</evaluationMessage>
        </expectation>
      </instructionResult>
      <instructionResult>
        <instruction>{id='decisionTable_1_26', instruction='call', instanceName='decisionTable_1', methodName='sprawdzCzyKartaNieZablokowana', args=[]}</instruction>
        <slimResult>pass(true)</slimResult>
        <expectation>
          <status>pass</status>
          <instructionId>decisionTable_1_26</instructionId>
          <col>5</col>
          <row>4</row>
          <type>ReturnedValueExpectation</type>
          <evaluationMessage>true</evaluationMessage>
        </expectation>
      </instructionResult>
      <instructionResult>
        <instruction>{id='decisionTable_1_28', instruction='call', instanceName='decisionTable_1', methodName='setIdKarty', args=[1001]}</instruction>
        <slimResult></slimResult>
        <expectation>
          <instructionId>decisionTable_1_28</instructionId>
          <col>0</col>
          <row>5</row>
          <type>VoidReturnExpectation</type>
        </expectation>
      </instructionResult>
      <instructionResult>
        <instruction>{id='decisionTable_1_29', instruction='call', instanceName='decisionTable_1', methodName='setPin', args=[9999]}</instruction>
        <slimResult></slimResult>
        <expectation>
          <instructionId>decisionTable_1_29</instructionId>
          <col>1</col>
          <row>5</row>
          <type>VoidReturnExpectation</type>
        </expectation>
      </instructionResult>
      <instructionResult>
        <instruction>{id='decisionTable_1_30', instruction='call', instanceName='decisionTable_1', methodName='setKwotaWyplaty', args=[100.00]}</instruction>
        <slimResult></slimResult>
        <expectation>
          <instructionId>decisionTable_1_30</instructionId>
          <col>2</col>
          <row>5</row>
          <type>VoidReturnExpectation</type>
        </expectation>
      </instructionResult>
      <instructionResult>
        <instruction>{id='decisionTable_1_32', instruction='call', instanceName='decisionTable_1', methodName='wykonajWyplateGotowki', args=[]}</instruction>
        <slimResult>pass(false)</slimResult>
        <expectation>
          <status>pass</status>
          <instructionId>decisionTable_1_32</instructionId>
          <col>3</col>
          <row>5</row>
          <type>ReturnedValueExpectation</type>
          <evaluationMessage>false</evaluationMessage>
        </expectation>
      </instructionResult>
      <instructionResult>
        <instruction>{id='decisionTable_1_33', instruction='call', instanceName='decisionTable_1', methodName='sprawdzSaldoPoWyplacie', args=[]}</instruction>
        <slimResult>pass(700.0)</slimResult>
        <expectation>
          <status>pass</status>
          <instructionId>decisionTable_1_33</instructionId>
          <col>4</col>
          <row>5</row>
          <type>ReturnedValueExpectation</type>
          <evaluationMessage>700.0</evaluationMessage>
        </expectation>
      </instructionResult>
      <instructionResult>
        <instruction>{id='decisionTable_1_34', instruction='call', instanceName='decisionTable_1', methodName='sprawdzCzyKartaNieZablokowana', args=[]}</instruction>
        <slimResult>pass(true)</slimResult>
        <expectation>
          <status>pass</status>
          <instructionId>decisionTable_1_34</instructionId>
          <col>5</col>
          <row>5</row>
          <type>ReturnedValueExpectation</type>
          <evaluationMessage>true</evaluationMessage>
        </expectation>
      </instructionResult>
      <instructionResult>
        <instruction>{id='decisionTable_1_36', instruction='call', instanceName='decisionTable_1', methodName='setIdKarty', args=[1003]}</instruction>
        <slimResult></slimResult>
        <expectation>
          <instructionId>decisionTable_1_36</instructionId>
          <col>0</col>
          <row>6</row>
          <type>VoidReturnExpectation</type>
        </expectation>
      </instructionResult>
      <instructionResult>
        <instruction>{id='decisionTable_1_37', instruction='call', instanceName='decisionTable_1', methodName='setPin', args=[9999]}</instruction>
        <slimResult></slimResult>
        <expectation>
          <instructionId>decisionTable_1_37</instructionId>
          <col>1</col>
          <row>6</row>
          <type>VoidReturnExpectation</type>
        </expectation>
      </instructionResult>
      <instructionResult>
        <instruction>{id='decisionTable_1_38', instruction='call', instanceName='decisionTable_1', methodName='setKwotaWyplaty', args=[6000.00]}</instruction>
        <slimResult></slimResult>
        <expectation>
          <instructionId>decisionTable_1_38</instructionId>
          <col>2</col>
          <row>6</row>
          <type>VoidReturnExpectation</type>
        </expectation>
      </instructionResult>
      <instructionResult>
        <instruction>{id='decisionTable_1_40', instruction='call', instanceName='decisionTable_1', methodName='wykonajWyplateGotowki', args=[]}</instruction>
        <slimResult>pass(false)</slimResult>
        <expectation>
          <status>pass</status>
          <instructionId>decisionTable_1_40</instructionId>
          <col>3</col>
          <row>6</row>
          <type>ReturnedValueExpectation</type>
          <evaluationMessage>false</evaluationMessage>
        </expectation>
      </instructionResult>
      <instructionResult>
        <instruction>{id='decisionTable_1_41', instruction='call', instanceName='decisionTable_1', methodName='sprawdzSaldoPoWyplacie', args=[]}</instruction>
        <slimResult>pass(2500.0)</slimResult>
        <expectation>
          <status>pass</status>
          <instructionId>decisionTable_1_41</instructionId>
          <col>4</col>
          <row>6</row>
          <type>ReturnedValueExpectation</type>
          <evaluationMessage>2500.0</evaluationMessage>
        </expectation>
      </instructionResult>
      <instructionResult>
        <instruction>{id='decisionTable_1_42', instruction='call', instanceName='decisionTable_1', methodName='sprawdzCzyKartaNieZablokowana', args=[]}</instruction>
        <slimResult>pass(true)</slimResult>
        <expectation>
          <status>pass</status>
          <instructionId>decisionTable_1_42</instructionId>
          <col>5</col>
          <row>6</row>
          <type>ReturnedValueExpectation</type>
          <evaluationMessage>true</evaluationMessage>
        </expectation>
      </instructionResult>
    </instructions>
  </result>
  <executionLog>
    <testSystem></testSystem>
    <command></command>
    <exitCode>0</exitCode>
    <stdOut>[LOG] Pomyślna weryfikacja tożsamości dla karty: 1001

[LOG] Zmiana salda karty 1001 o kwotę: -100

[LOG] Zrealizowano wypłatę gotówki: 100.0 z karty: 1001

[LOG] Pomyślna weryfikacja tożsamości dla karty: 1001

[LOG] Zmiana salda karty 1001 o kwotę: -200

[LOG] Zrealizowano wypłatę gotówki: 200.0 z karty: 1001

[LOG] Pomyślna weryfikacja tożsamości dla karty: 1002

[LOG] Zmiana salda karty 1002 o kwotę: -50

[LOG] Zrealizowano wypłatę gotówki: 50.0 z karty: 1002

[LOG] Nieudana weryfikacja tożsamości dla karty: 1001

[LOG] Pomyślna weryfikacja tożsamości dla karty: 1003

[LOG] Przekroczono maksymalną kwotę wypłaty

[LOG] Nie udało się zrealizować wypłaty gotówki: 6000.0

</stdOut>
    <stdErr></stdErr>
  </executionLog>
  <finalCounts>
    <right>1</right>
    <wrong>0</wrong>
    <ignores>0</ignores>
    <exceptions>0</exceptions>
  </finalCounts>
  <totalRunTimeInMillis>62</totalRunTimeInMillis>
</testResults>

